FairLangProc/__init__.py
FairLangProc/algorithms/__init__.py
FairLangProc/algorithms/output.py
FairLangProc/algorithms/inprocessors/__init__.py
FairLangProc/algorithms/inprocessors/adapter.py
FairLangProc/algorithms/inprocessors/regularizers.py
FairLangProc/algorithms/inprocessors/selective_updating.py
FairLangProc/algorithms/intraprocessors/__init__.py
FairLangProc/algorithms/intraprocessors/modular.py
FairLangProc/algorithms/intraprocessors/redistribution.py
FairLangProc/algorithms/preprocessors/__init__.py
FairLangProc/algorithms/preprocessors/augmentation.py
FairLangProc/algorithms/preprocessors/projection_based.py
FairLangProc/algorithms/preprocessors/reweighting.py
FairLangProc/datasets/__init__.py
FairLangProc/datasets/fairness_datasets.py
FairLangProc/metrics/__init__.py
FairLangProc/metrics/embedding.py
FairLangProc/metrics/generated_text.py
FairLangProc/metrics/probability.py
docs/conf.py
fairlangproc-0.1.3.dist-info/licenses/LICENSE
notebooks/RunDemoDebiasing.py
tests/TestDatasets.py
tests/TestMetricsEmbedding.py
tests/TestMetricsProbability.py
tests/TestMetricsText.py
tests/TestModels.py
tests/__init__.py
fairlangproc-0.1.3.dist-info/METADATA
fairlangproc-0.1.3.dist-info/WHEEL
fairlangproc-0.1.3.dist-info/top_level.txt
fairlangproc-0.1.3.dist-info/RECORD
