Metadata-Version: 2.4
Name: FairLangProc
Version: 0.1.3
Summary: A comprehensive set of fairness metrics, datasets and algorithms to address and mitigate bias in Natural Language Processing.
Author-email: Arturo Pérez-Peralta <arturopll55@gmail.com>
License: MIT
Project-URL: Homepage, https://github.com/arturo-perez-peralta/FairLangProc
Classifier: Programming Language :: Python :: 3
Classifier: License :: OSI Approved :: MIT License
Classifier: Operating System :: OS Independent
Requires-Python: >=3.10
License-File: LICENSE
Requires-Dist: transformers
Requires-Dist: torch
Requires-Dist: numpy
Requires-Dist: datasets
Requires-Dist: pandas
Requires-Dist: scikit-learn
Requires-Dist: adapter-transformers
Requires-Dist: pytest
Dynamic: license-file
